jonsnow/__init__.py
jonsnow-0.0.2.dist-info/DESCRIPTION.rst
jonsnow-0.0.2.dist-info/METADATA
jonsnow-0.0.2.dist-info/RECORD
jonsnow-0.0.2.dist-info/WHEEL
jonsnow-0.0.2.dist-info/entry_points.txt
jonsnow-0.0.2.dist-info/metadata.json
jonsnow-0.0.2.dist-info/top_level.txt
