Metadata-Version: 2.0
Name: jonsnow
Version: 0.0.2
Summary: A simple tool to run a shell command when files change.
Home-page: https://github.com/galbacarys/jonsnow
Author: Gabriel Albacarys
Author-email: nameless912@gmail.com
License: MIT
Keywords: development build buildtools automation
Platform: UNKNOWN
Classifier: Development Status :: 3 - Alpha
Classifier: Environment :: Console
Classifier: Intended Audience :: Developers
Classifier: License :: OSI Approved :: MIT License
Classifier: Natural Language :: English
Classifier: Operating System :: OS Independent
Classifier: Topic :: Utilities
Classifier: Programming Language :: Python :: 3
